Lab2/verilog/inputconditioner.v
//------------------------------------------------------------------------
// Input Conditioner
//    1) Synchronizes input to clock domain
//    2) Debounces input
//    3) Creates pulses at edge transitions
//------------------------------------------------------------------------

module inputconditioner
(
input 	    clk,            // Clock domain to synchronize input to
input	    noisysignal,    // (Potentially) noisy input signal
output reg  conditioned,    // Conditioned output signal
output reg  positiveedge,   // 1 clk pulse at rising edge of conditioned
output reg  negativeedge    // 1 clk pulse at falling edge of conditioned
);

    parameter counterwidth = 3; // Counter size, in bits, >= log2(waittime)
    parameter waittime = 3;     // Debounce delay, in clock cycles
    
    reg[counterwidth-1:0] counter = 0;
    reg synchronizer0 = 0;
    reg synchronizer1 = 0;
    
    always @(posedge clk ) begin
        // make sure that positiveedge and negativeedge only last for one clock cycle
        positiveedge <= 0;
        negativeedge <= 0;
        if(conditioned == synchronizer1) begin
            counter <= 0;
        end else begin
            if( counter == waittime) begin
                counter <= 0;
                conditioned <= synchronizer1;
                positiveedge <= synchronizer1;  // set positiveedge to the value of synchronizer1 
                // under the if statement that synchronizer1 is not equal to conditioned
                negativeedge <= !synchronizer1;  // set negativeedge to the value of not synchronizer1 
                // under the if statement that synchronizer1 is not equal to conditioned
            end
            else begin
                counter <= counter+1;
            end
        end
        synchronizer0 <= noisysignal;
        synchronizer1 <= synchronizer0;
    end
endmodule

Lab2/verilog/inputconditioner.t.v
//------------------------------------------------------------------------
// Input Conditioner test bench
//------------------------------------------------------------------------
module testConditioner();

    wire clk;
    wire pin;
    wire conditioned;
    wire rising;
    wire falling;

    reg begintest;
    wire dutpassed;
    
    inputconditioner dut(.clk(clk),
    			 .noisysignal(pin),
			 .conditioned(conditioned),
			 .positiveedge(rising),
			 .negativeedge(falling));


    inputcondtestbench test(.begintest(begintest),
                            .endtest(endtest),
                            .dutpassed(dutpassed),
                            .clk(clk),
                            .pin(pin),
                            .conditioned(conditioned),
                            .rising(rising),
                            .falling(falling));


    // Generate clock (50MHz)
    initial begin
        begintest = 0;
        #10;
        begintest = 1;
        #10000;
    end

    // Display test results ('dutpassed' signal) once 'endtest' goes high
    always @(posedge endtest) begin
        if (dutpassed == 1) begin
            $display("\n\033[32mDUT passed?: %b\033[37m\n", dutpassed);
        end else begin
            $display("\n\033[31mDUT passed?: %b\033[37m\n", dutpassed);
        end
    end
    
    // Your Test Code
    // Be sure to test each of the three conditioner functions:
    // Synchronize, Clean, Preprocess (edge finding)
    
endmodule

module inputcondtestbench (
    input           begintest,  // Triggers start of testing
    output reg      endtest,    // Raise once test completes
    output reg      dutpassed,  // Signal test result)

    output reg      clk,
    output reg      pin,
    input           conditioned,
    input           rising,
    input           falling);

    initial begin
        $dumpfile("../wave/testConditioner.vcd");
        $dumpvars(0, inputcondtestbench);
        clk = 0;
        pin = 1;
    end

    /* Will test for the following:
        1. Synchronization - 
        2. Clean - change inputs many times within 3 clock cycles, should output the final value
        3. Preprocess - Change inputs so that we can detect edge changes in conditioned
    */

    always begin
        #5 clk = !clk;
    end

    always @(posedge begintest) begin
        endtest = 0;
        dutpassed = 1;

        // Test Case 2: Change input as follows: 101100 to simulate noise. Output should be 1.
        #5 pin = 0; // sync0 = 1, sync1 = 0, conditioned = x, counter = 0
        #5 pin = 1; 
        #5 pin = 1; // sync0 = 0, sync1 = 1, conditioned = x, counter = 1
        #5 pin = 0;
        #5 pin = 0; #60 // sync0 = 1, sync1 = 0, conditioned = x, counter = 2

        /* What happens at every posedge: 
            - sync0 = 1, sync1 = 1, conditioned = x, counter = 3
            - sync0 = 1, sync1 = 1, conditioned = x, counter = 0
            - sync0 = 1, sync1 = 1, conditioned = x, counter = 1
            - sync0 = 1, sync1 = 1, conditioned = x, counter = 2
            - sync0 = 1, sync1 = 1, conditioned = x, counter = 3
            - sync0 = 1, sync1 = 1, conditioned = 1, counter = 0
        */
        // $display("CONDITIONED: %b | RISING: %b | FALLING: %b", conditioned, rising, falling);
        if ((conditioned != 0) || (rising != 0) || (falling != 0)) begin
            dutpassed = 0;
            $display("Test Case 1 Failed"); 
        end

        // Test Case 3: Change input as follows: 0 then hold until conditioned changes, then input = 1 then hold until conditioned changes
        #5 pin = 1; #65 // wait until correct clock rise

        // $display("CONDITIONED: %b | RISING: %b | FALLING: %b", conditioned, rising, falling);
        if ((conditioned != 1) || (rising != 1) || (falling != 0)) begin
            dutpassed = 0;
            $display("Test Case 2 Failed"); 
        end

        #5 pin = 0; #65 // wait until correct clock rise

        // $display("CONDITIONED: %b | RISING: %b | FALLING: %b", conditioned, rising, falling);
        if ((conditioned != 0) || (rising != 0) || (falling != 1)) begin
            dutpassed = 0;
            $display("Test Case 3 Failed"); 
        end

        #5 endtest = 1;
        $finish;
    end

endmodule

Lab2/wave/testConditioner.vcd
$date
	Mon Nov  9 16:04:00 2015
$end
$version
	Icarus Verilog
$end
$timescale
	1s
$end
$scope module testConditioner $end
$scope module test $end
$var wire 1 ! begintest $end
$var wire 1 " conditioned $end
$var wire 1 # falling $end
$var wire 1 $ rising $end
$var reg 1 % clk $end
$var reg 1 & dutpassed $end
$var reg 1 ' endtest $end
$var reg 1 ( pin $end
$upscope $end
$upscope $end
$enddefinitions $end
#0
$dumpvars
1(
x'
x&
0%
x$
x#
x"
0!
$end
#5
0#
0$
1%
#10
1&
0'
0%
1!
#15
0(
1%
#20
1(
0%
#25
1%
#30
0(
0%
#35
1#
0"
1%
#40
0%
#45
0#
1%
#50
0%
#55
1%
#60
0%
#65
1%
#70
0%
#75
1%
#80
0%
#85
1%
#90
0%
#95
1%
#100
0%
1(
#105
1%
#110
0%
#115
1%
#120
0%
#125
1%
#130
0%
#135
1%
#140
0%
#145
1%
#150
0%
#155
1$
1"
1%
#160
0%
#165
0$
1%
#170
0%
0(
#175
1%
#180
0%
#185
1%
#190
0%
#195
1%
#200
0%
#205
1%
#210
0%
#215
1%
#220
0%
#225
1#
0"
1%
#230
0%
#235
0#
1%
#240
0%
#241
1(
#244
0(
#245
1%
#247
1(
#250
0(
0%
#253
1(
#255
1%
#260
0%
#265
1%
#270
0%
#275
1%
#280
0%
#285
1%
#290
0%
#295
1%
#300
0%
#305
1$
1"
1%
#310
0%
#315
0$
1%
1'
