Lab2/verilog/shiftregister.v
//------------------------------------------------------------------------
// Shift Register
//   Parameterized width (in bits)
//   Shift register can operate in two modes:
//      - serial in, parallel out
//      - parallel in, serial out
//------------------------------------------------------------------------

module shiftregister
	#(parameter width = 8)
	(
	input               clk,                // FPGA Clock
	input               peripheralClkEdge,  // Edge indicator
	input               parallelLoad,       // 1 = Load shift reg with parallelDataIn
	input  [width-1:0]  parallelDataIn,     // Load shift reg in parallel
	input               serialDataIn,       // Load shift reg serially
	output [width-1:0]  parallelDataOut,    // Shift reg data contents
	output              serialDataOut       // Positive edge synchronized
	);

    reg [width-1:0] shiftregistermem;

    always @(posedge clk) begin

        if (parallelLoad == 1) begin
            shiftregistermem <= parallelDataIn;
        end else begin
            if (peripheralClkEdge == 1) begin
        		shiftregistermem <= shiftregistermem << 1;
                shiftregistermem[0] <= serialDataIn;
            end
    end

    assign serialDataOut = shiftregistermem[7];
    assign parallelDataOut = shiftregistermem;

endmodule

// module test();
// 	reg clk, peripheralClkEdge, parallelLoad, serialDataIn;
// 	reg [7:0] parallelDataIn;
// 	wire [7:0] parallelDataOut;
// 	wire serialDataOut;

// 	shiftregister shiftreg(clk, peripheralClkEdge, parallelLoad, parallelDataIn, serialDataIn, parallelDataOut, serialDataOut);

// 	initial begin
// 		clk = 0; #10
// 		clk = 1; peripheralClkEdge = 1; parallelLoad = 0; parallelDataIn = 8'b01110011; serialDataIn = 1; #10 
// 		clk = 0; #10 clk = 1; #10 clk = 0; #10 clk = 1; #10
// 		$display("Parallel-in: %b | Serial-out: %b | Parallel-out: %b", shiftreg.parallelDataIn, shiftreg.serialDataOut, shiftreg.parallelDataOut);
// 	end
// endmodule

Lab2/shiftregister.t.v
//------------------------------------------------------------------------
// Shift Register test bench
//------------------------------------------------------------------------

module testshiftregister();

    wire             clk;
    wire             peripheralClkEdge;
    wire             parallelLoad;
    wire[7:0]        parallelDataOut;
    wire             serialDataOut;
    wire[7:0]        parallelDataIn;
    wire             serialDataIn; 
    
    reg     begintest;  // Set High to begin testing register file
    wire      dutpassed;  // Indicates whether register file passed tests

    // Instantiate with parameter width = 8
    shiftregister #(8) dut(.clk(clk), 
    		           .peripheralClkEdge(peripheralClkEdge),
    		           .parallelLoad(parallelLoad), 
    		           .parallelDataIn(parallelDataIn), 
    		           .serialDataIn(serialDataIn), 
    		           .parallelDataOut(parallelDataOut), 
    		           .serialDataOut(serialDataOut));

    // Instantiate test bench to test the DUT
    shiftregtestbench test(.begintest(begintest),
                        .endtest(endtest), 
                        .dutpassed(dutpassed),
                        .clk(clk),
                        .peripheralClkEdge(peripheralClkEdge),
                        .parallelLoad(parallelLoad), 
                        .parallelDataIn(parallelDataIn), 
                        .serialDataIn(serialDataIn), 
                        .parallelDataOut(parallelDataOut), 
                        .serialDataOut(serialDataOut));
    
    initial begin
    	begintest=0;
        #10;
        begintest=1;
        #10000;
    end

    // Display test results ('dutpassed' signal) once 'endtest' goes high
    always @(posedge endtest) begin
        $display("DUT passed?: %b", dutpassed);
    end

endmodule

module shiftregtestbench 
(
// Test bench driver signal connections
input           begintest,  // Triggers start of testing
output reg      endtest,    // Raise once test completes
output reg      dutpassed,  // Signal test result

input                  serialDataOut,      // Positive edge synchronized
input [7:0]            parallelDataOut,    // Shift reg data contents
output reg             clk,                // FPGA Clock
output reg             peripheralClkEdge,  // Edge indicator
output reg             parallelLoad,       // 1 = Load shift reg with parallelDataIn
output reg[7:0]        parallelDataIn,     // Load shift reg in parallel
output reg             serialDataIn        // Load shift reg serially
);

    // Initialize register driver signals
    initial begin
        clk = 0;
        peripheralClkEdge = 0;
        parallelLoad = 0;
        parallelDataIn = 0;
        serialDataIn = 0;
    end

        // Once 'begintest' is asserted, start running test cases
    always @(posedge begintest) begin
        endtest = 0;
        dutpassed = 1;
        #10

// Test Case 1: 

        //  Write 1 - 0 - 0 - 1 - 0 - 0 - 1 - 0 to the serial input
        //  Write 1 - 0 - 0 - 1 - 0 - 0 - 1 - 0 to the paralell input (opposite as serial)
        //  Set peripheralClkEdge to '1' and parallelLoad to '0'
        //  Verify with the serivalDataout and ParallelDataout
        //
        //  In this test, DUT are expected to be a fully perfect 
        //  serial-in-paralell-out 8-bit shift register. 
        //
        //  Device described as the following will be reported as error:
        //  1. broken peripheralClkEdge or broken parallelLoad (always set to '0' or '1')
        //  2. broken data input (choosing wrong data input)
        //  3. registers cannot shift correctly 
        //  4. serial output not outputing LSB
        //  5. broken paralell output
        peripheralClkEdge = 1;
        parallelLoad = 0;
        parallelDataIn = 146;
        serialDataIn = 1;

        #5 clk=1; #5 clk=0;   // Generate single clock pulse

        serialDataIn = 0;

        #5 clk=1; #5 clk=0;   // Generate single clock pulse

        serialDataIn = 0;

        #5 clk=1; #5 clk=0;   // Generate single clock pulse

        serialDataIn = 1;

        #5 clk=1; #5 clk=0;   // Generate single clock pulse

        serialDataIn = 0;

        #5 clk=1; #5 clk=0;   // Generate single clock pulse

        serialDataIn = 0;

        #5 clk=1; #5 clk=0;   // Generate single clock pulse

        serialDataIn = 1;

        #5 clk=1; #5 clk=0;   // Generate single clock pulse

        serialDataIn = 0;

        #5 clk=1; #5 clk=0;   // Generate single clock pulse

        // Verify expectations and report test result
        //   at this point, the serial output should be 1, the first number we write
        //   the parallel output should be 01001001, which is 73
        if((serialDataOut != 1) || (parallelDataOut != 73)) begin  
          dutpassed = 0;  
          $display("Test Case 1 Failed");
        end

        #5 clk=1; #5 clk=0;   // Generate single clock pulse

        // Verify expectations and report test result
        //   at this point, the serial output should be 0, the second number we write
        //   the parallel output should be 00100100, which is 36
        if((serialDataOut != 0) || (parallelDataOut != 36)) begin  
          dutpassed = 0;  
          $display("Test Case 1 Failed");
        end

        #5 clk=1; #5 clk=0;   // Generate single clock pulse

        // Verify expectations and report test result
        //   at this point, the serial output should be 0, the third number we write
        //   the parallel output should be 00010010, which is 18
        if((serialDataOut != 0) || (parallelDataOut != 18)) begin  
          dutpassed = 0;  
          $display("Test Case 1 Failed");
        end

        #5 clk=1; #5 clk=0;   // Generate single clock pulse

        // Verify expectations and report test result
        //   at this point, the serial output should be 1, the fourth number we write
        //   the parallel output should be 00001001, which is 9
        if((serialDataOut != 1) || (parallelDataOut != 18)) begin  
          dutpassed = 0;  
          $display("Test Case 1 Failed");
        end

        #5 clk=1; #5 clk=0;   // Generate single clock pulse

        // Verify expectations and report test result
        //   at this point, the serial output should be 0, the fifth number we write
        //   the parallel output should be 00000100, which is 4
        if((serialDataOut != 0) || (parallelDataOut != 4)) begin  
          dutpassed = 0;  
          $display("Test Case 1 Failed");
        end

        #5 clk=1; #5 clk=0;   // Generate single clock pulse

        // Verify expectations and report test result
        //   at this point, the serial output should be 0, the sixth number we write
        //   the parallel output should be 00000010, which is 2
        if((serialDataOut != 0) || (parallelDataOut != 2)) begin  
          dutpassed = 0;  
          $display("Test Case 1 Failed");
        end

        #5 clk=1; #5 clk=0;   // Generate single clock pulse

        // Verify expectations and report test result
        //   at this point, the serial output should be 0, the seventh number we write
        //   the parallel output should be 0000001, which is 1
        if((serialDataOut != 0) || (parallelDataOut != 1)) begin  
          dutpassed = 0;  
          $display("Test Case 1 Failed");
        end

        #5 clk=1; #5 clk=0;   // Generate single clock pulse

        // Verify expectations and report test result
        //   at this point, the serial output should be 0, the eighth number we write
        //   the parallel output should be 0000000, which is 0
        if((serialDataOut != 0) || (parallelDataOut != 0)) begin  
          dutpassed = 0;  
          $display("Test Case 1 Failed");
        end

        #5

// Test Case 2: 

        //  Write 1 to the serial input (oppsite MSB as paralell)
        //  Write 0 - 0 - 1 - 1 - 1 - 0 - 1 - 1 to the paralell input
        //  Verify with the serivalDataout and ParallelDataout
        //
        //  In this test, DUT are expected to be a fully perfect 
        //  paralell-in-serial-out 8-bit shift register. 
        //
        //  Device described as the following will be reported as error:
        //  1. broken parallelLoad or broken peripheralClkEdge (always set to '0' or '1') (always set to '0' or '1')
        //  2. broken data input (choosing wrong data input)
        //  3. registers cannot shift correctly 
        //  4. serial output not outputing LSB
        //  5. broken paralell output
        peripheralClkEdge = 0;
        parallelLoad = 1;
        parallelDataIn = 59;
        serialDataIn = 1;

        #5 clk=1; #5 clk=0;   // Generate single clock pulse

        // Verify expectations and report test result
        //   at this point, the serial output should be 1, the LSB in paralell input
        //   the parallel output should be 00111011, which is 59
        if((serialDataOut != 1) || (parallelDataOut != 59)) begin  
          dutpassed = 0;  
          $display("Test Case 2 Failed");
        end

        #5 clk=1; #5 clk=0;   // Generate single clock pulse

        // Verify expectations and report test result
        //   at this point, the serial output should be 1, the second LSB in paralell input
        //   the parallel output should be 00011101, which is 29
        if((serialDataOut != 1) || (parallelDataOut != 29)) begin  
          dutpassed = 0;  
          $display("Test Case 2 Failed");
        end

        #5 clk=1; #5 clk=0;   // Generate single clock pulse

        // Verify expectations and report test result
        //   at this point, the serial output should be 0, the third LSB in paralell input
        //   the parallel output should be 00001110, which is 14
        if((serialDataOut != 0) || (parallelDataOut != 14)) begin  
          dutpassed = 0;  
          $display("Test Case 2 Failed");
        end

        #5 clk=1; #5 clk=0;   // Generate single clock pulse

        // Verify expectations and report test result
        //   at this point, the serial output should be 1, the fourth LSB in paralell input
        //   the parallel output should be 00000111, which is 7
        if((serialDataOut != 1) || (parallelDataOut != 7)) begin  
          dutpassed = 0;  
          $display("Test Case 2 Failed");
        end

        #5 clk=1; #5 clk=0;   // Generate single clock pulse

        // Verify expectations and report test result
        //   at this point, the serial output should be 1, the fifth LSB in paralell input
        //   the parallel output should be 00000011, which is 3
        if((serialDataOut != 1) || (parallelDataOut != 3)) begin  
          dutpassed = 0;  
          $display("Test Case 2 Failed");
        end

        #5 clk=1; #5 clk=0;   // Generate single clock pulse

        // Verify expectations and report test result
        //   at this point, the serial output should be 1, the sixth LSB in paralell input
        //   the parallel output should be 00000001, which is 1
        if((serialDataOut != 1) || (parallelDataOut != 1)) begin  
          dutpassed = 0;  
          $display("Test Case 2 Failed");
        end

        #5 clk=1; #5 clk=0;   // Generate single clock pulse

        // Verify expectations and report test result
        //   at this point, the serial output should be 0, the seventh LSB in paralell input
        //   the parallel output should be 00000000, which is 0
        if((serialDataOut != 0) || (parallelDataOut != 0)) begin  
          dutpassed = 0;  
          $display("Test Case 2 Failed");
        end

        #5 clk=1; #5 clk=0;   // Generate single clock pulse

        // Verify expectations and report test result
        //   at this point, the serial output should be 0, the eighth LSB in paralell input
        //   the parallel output should be 00000000, which is 0
        if((serialDataOut != 0) || (parallelDataOut != 0)) begin  
          dutpassed = 0;  
          $display("Test Case 2 Failed");
        end

        #5
        endtest = 1;
    end

endmodule

Lab2/wave/testShiftRegister.vcd
$date
	Mon Nov  9 16:04:23 2015
$end
$version
	Icarus Verilog
$end
$timescale
	1s
$end
$scope module testshiftregister $end
$scope module test $end
$var wire 1 ! begintest $end
$var wire 8 " parallelDataOut [7:0] $end
$var wire 1 # serialDataOut $end
$var reg 1 $ clk $end
$var reg 1 % dutpassed $end
$var reg 1 & endtest $end
$var reg 8 ' parallelDataIn [7:0] $end
$var reg 1 ( parallelLoad $end
$var reg 1 ) peripheralClkEdge $end
$var reg 1 * serialDataIn $end
$upscope $end
$upscope $end
$enddefinitions $end
#0
$dumpvars
0*
0)
0(
b0 '
x&
x%
0$
x#
bx "
0!
$end
#5
1$
#10
1%
0&
0$
1!
#15
1$
#20
0$
1*
b10010010 '
1)
#25
bx1 "
1$
#30
0$
0*
#35
bx10 "
1$
#40
0$
#45
bx100 "
1$
#50
0$
1*
#55
bx1001 "
1$
#60
0$
0*
#65
bx10010 "
1$
#70
0$
#75
bx100100 "
1$
#80
0$
1*
#85
bx1001001 "
1$
#90
0$
0*
#95
1#
b10010010 "
1$
#100
0$
#105
0#
b100100 "
1$
#110
0$
#115
b1001000 "
1$
#120
0$
#125
1#
b10010000 "
1$
#130
0$
#135
0#
b100000 "
1$
#140
0$
#145
b1000000 "
1$
#150
0$
#155
1#
b10000000 "
1$
#160
0$
#165
0#
b0 "
1$
#170
0$
#175
b111011 "
1$
1*
b111011 '
1(
#180
0$
#185
1$
b10000000 '
0(
0)
#190
0$
#195
1$
#200
0$
1&
